Workbook
Name Fruits: 'Data Validation'!$C$76:$C$84
Name Meats: 'Data Validation'!$D$76:$D$79
Name Vegetables: 'Data Validation'!$B$76:$B$84

Sheet Goal Seek
A2: Loan Amount | B2: 3000000
A3: Payment period | B3: 10
A4: Interest Rate | B4: 0.18181818
A5: Payment Amount | B5: =E18 -> 6000000
A7: Loan Schedule | B7: Loan Balance | C7: Interest | D7: Principal | E7: Total Payment | G7: Loan Schedule | H7: Loan Balance | I7: Interest | J7: Principal | K7: Total Payment
A8: Y1 | B8: =B2 -> 3000000 | C8: =B8*$B$4 -> 545454.55 | D8: =$B$8/10 -> 300000 | E8: =C8+D8 -> 845454.55 | G8: Y1 | H8: =B8 -> 3000000 | I8: =H8*B4 -> 545454.55 | J8: =$B$8/$B$3 -> 300000 | K8: =I8+J8 -> 845454.55
A9: Y2 | B9: =B8-D8 -> 2700000 | C9: =B9*$B$4 -> 490909.09 | D9: =$B$8/10 -> 300000 | E9: =C9+D9 -> 790909.09 | G9: Y2 | H9: =H8-J8 -> 2700000 | I9: =H9*B4 -> 490909.09 | J9: =$B$8/$B$3 -> 300000 | K9: =I9+J9 -> 790909.09
A10: Y3 | B10: =B9-D9 -> 2400000 | C10: =B10*$B$4 -> 436363.64 | D10: =$B$8/10 -> 300000 | E10: =C10+D10 -> 736363.64 | G10: Y3 | H10: =H9-J9 -> 2400000 | I10: =H10*B4 -> 436363.64 | J10: =$B$8/$B$3 -> 300000 | K10: =I10+J10 -> 736363.64
A11: Y4 | B11: =B10-D10 -> 2100000 | C11: =B11*$B$4 -> 381818.18 | D11: =$B$8/10 -> 300000 | E11: =C11+D11 -> 681818.18 | G11: Y4 | H11: =H10-J10 -> 2100000 | I11: =H11*B4 -> 381818.18 | J11: =$B$8/$B$3 -> 300000 | K11: =I11+J11 -> 681818.18
A12: Y5 | B12: =B11-D11 -> 1800000 | C12: =B12*$B$4 -> 327272.73 | D12: =$B$8/10 -> 300000 | E12: =C12+D12 -> 627272.73 | G12: Y5 | H12: =H11-J11 -> 1800000 | I12: =H12*B4 -> 327272.73 | J12: =$B$8/$B$3 -> 300000 | K12: =I12+J12 -> 627272.73
A13: Y6 | B13: =B12-D12 -> 1500000 | C13: =B13*$B$4 -> 272727.27 | D13: =$B$8/10 -> 300000 | E13: =C13+D13 -> 572727.27 | G13: Y6 | H13: =H12-J12 -> 1500000 | I13: =H13*B4 -> 272727.27 | J13: =$B$8/$B$3 -> 300000 | K13: =I13+J13 -> 572727.27
A14: Y7 | B14: =B13-D13 -> 1200000 | C14: =B14*$B$4 -> 218181.82 | D14: =$B$8/10 -> 300000 | E14: =C14+D14 -> 518181.82 | G14: Y7 | H14: =H13-J13 -> 1200000 | I14: =H14*B4 -> 218181.82 | J14: =$B$8/$B$3 -> 300000 | K14: =I14+J14 -> 518181.82
A15: Y8 | B15: =B14-D14 -> 900000 | C15: =B15*$B$4 -> 163636.36 | D15: =$B$8/10 -> 300000 | E15: =C15+D15 -> 463636.36 | G15: Y8 | H15: =H14-J14 -> 900000 | I15: =H15*B4 -> 163636.36 | J15: =$B$8/$B$3 -> 300000 | K15: =I15+J15 -> 463636.36
A16: Y9 | B16: =B15-D15 -> 600000 | C16: =B16*$B$4 -> 109090.91 | D16: =$B$8/10 -> 300000 | E16: =C16+D16 -> 409090.91 | G16: Y9 | H16: =H15-J15 -> 600000 | I16: =H16*B4 -> 109090.91 | J16: =$B$8/$B$3 -> 300000 | K16: =I16+J16 -> 409090.91
A17: Y10 | B17: =B16-D16 -> 300000 | C17: =B17*$B$4 -> 54545.455 | D17: =$B$8/10 -> 300000 | E17: =C17+D17 -> 354545.45 | G17: Y10 | H17: =H16-J16 -> 300000 | I17: =H17*B4 -> 54545.455 | J17: =$B$8/$B$3 -> 300000 | K17: =I17+J17 -> 354545.45
E18: =SUM(E8:E17) -> 6000000 | K18: =SUM(K8:K17) -> 6000000

Sheet Goal Seek 2
A1: Full Day Training
A3: Cost Item | B3: Amount | C3: Amount | F3: Gross Profit
A4: Hotel Conference Room | B4: 50000 | C4: 50000
A5: Feeding per participant | B5: 1200 | C5: 1200
A6: Training Material | B6: 3000 | C6: 3000
A7: Certificate | B7: 2000 | C7: 2000
A8: Prize for best participant | B8: 50000 | C8: 50000
A10: Analysis based on estimates | B10: Figure
A11: Number of participants | B11: 40 | C11: 43.859649
A12: Course Fee | B12: 20000 | C12: 20000
A13: Total Feeding cost | B13: =B11*B5 -> 48000 | C13: =C11*C5 -> 52631.579
A14: Conference Room cost | B14: =B4 -> 50000 | C14: =C4 -> 50000
A15: Training Materials cost | B15: =B6*B11 -> 120000 | C15: =C11*C6 -> 131578.95
A16: Certificate Costs | B16: =B7*B11 -> 80000 | C16: =C11*C7 -> 87719.298
A17: Prize Award cost | B17: =B8 -> 50000 | C17: =C8 -> 50000
A19: Total Revenue | B19: =B11*B12 -> 800000 | C19: =C11*C12 -> 877192.98
A20: Total Cost | B20: =SUM(B13:B17) -> 348000 | C20: =SUM(C13:C17) -> 371929.82
A21: TaxFee (5%) | B21: =B19*0.05 -> 40000 | C21: =C19*5% -> 43859.649
A22: Contigencies (7%) | B22: =B19*0.07 -> 56000 | C22: =C19*7% -> 61403.509
A23: Gross Profit | B23: =B19-SUM(B20:B22) -> 356000 | C23: =C19-SUM(C20:C22) -> 400000

Sheet Scenario Manager
A1: Full Day Training
A3: Cost Item | B3: Amount | F3: Gross Profit | G3: 1500000
A4: Hotel Conference Room | B4: 50000 | C4: 50000
A5: Feeding per participant | B5: 1200 | C5: 1200
A6: Training Material | B6: 3000 | C6: 3000
A7: Certificate | B7: 2000 | C7: 2000
A8: Prize for best participant | B8: 50000 | C8: 50000
A10: Analysis based on estimates
A11: Number of participants | B11: 40 | C11: 50
A12: Course Fee | B12: 20000 | C12: 22000
A13: Total Feeding cost | B13: =B11*B5 -> 48000 | C13: =C11*C5 -> 60000
A14: Conference Room cost | B14: =B4 -> 50000 | C14: =C4 -> 50000
A15: Training Materials cost | B15: =B11*B6 -> 120000 | C15: =C11*C6 -> 150000
A16: Certificate Costs | B16: =B11*B7 -> 80000 | C16: =C11*C7 -> 100000
A17: Prize Award cost | B17: =B8 -> 50000 | C17: =C8 -> 50000
A19: Total Revenue | B19: =B12*B11 -> 800000 | C19: =C12*C11 -> 1100000
A20: Total Cost | B20: =SUM(B13:B17) -> 348000 | C20: =SUM(C13:C17) -> 410000
A21: TaxFee (5%) | B21: =B19*5% -> 40000 | C21: =C19*5% -> 55000
A22: Contigencies (7%) | B22: =B19*7% -> 56000 | C22: =C19*7% -> 77000
A23: Gross Profit | B23: =B19-SUM(B20:B22) -> 356000 | C23: =C19-SUM(C20:C22) -> 558000

Sheet Scenario Summary
B2: Scenario Summary
D3: Current Values: | E3: Case1 | F3: case2 | G3: Case3
E4: Created by Muski on 08-01-2026 | F4: Created by Muski on 08-01-2026 | G4: Created by Muski on 08-01-2026
B5: Changing Cells:
C6: $C$11 | D6: 50 | E6: 40 | F6: 45 | G6: 50
C7: $C$12 | D7: 22000 | E7: 21000 | F7: 18000 | G7: 22000
B8: Result Cells:
C9: $C$23 | D9: 558000 | E9: 391200 | F9: 333800 | G9: 558000
B10: Notes: Current Values column represents values of changing cells at
B11: time Scenario Summary Report was created. Changing cells for each
B12: scenario are highlighted in gray.

Sheet Scenario Manager-2
C2: Scenario manager in excel is a part of three what-if-analysis tools . We can use it to see the impact of changing input values without changing the actual data.
D5: Worst case | E5: Most likely | F5: Best likely
D6: 0.02 | E6: 0.01 | F6: 0.06
D7: 0.03 | E7: 0.01 | F7: 0.06
D8: 0.05 | E8: 0.06 | F8: 0.01
C10: Qtr1 | D10: Qtr2 | E10: Qtr3 | F10: Qtr4 | G10: Annual | H10: Q to Q growth
B11: Sales | C11: 2490000 | D11: =C11+C11*$H$11 -> 2514900 | E11: =D11+D11*$H$11 -> 2540049 | F11: =E11+E11*$H$11 -> 2565449.5 | G11: =SUM(C11:F11) -> 10110398 | H11: 0.01
B12: COGS | C12: 1700000 | D12: =C12+C12*$H$12 -> 1717000 | E12: =D12+D12*$H$12 -> 1734170 | F12: =E12+E12*$H$12 -> 1751511.7 | G12: =SUM(C12:F12) -> 6902681.7 | H12: 0.01
B13: GP | C13: =C11-C12 -> 790000 | D13: =D11-D12 -> 797900 | E13: =E11-E12 -> 805879 | F13: =F11-F12 -> 813937.79 | G13: =SUM(C13:F13) -> 3207716.8
B14: Expenses | C14: 500000 | D14: =C14+C14*$H$14 -> 530000 | E14: =D14+D14*$H$14 -> 561800 | F14: =E14+E14*$H$14 -> 595508 | G14: =SUM(C14:F14) -> 2187308 | H14: 0.06
B15: Profit | C15: =C11-(C12+C14) -> 290000 | D15: =D11-(D12+D14) -> 267900 | E15: =E11-(E12+E14) -> 244079 | F15: =F11-(F12+F14) -> 218429.79 | G15: =SUM(C15:F15) -> 1020408.8

Sheet Data table 1 var
B1: Book Store
C3: Total Number Of Books | D3: % Sold For The Highest Price
C4: 100 | D4: 0.8
D6: Number of Books | E6: UnitProfit
C7: Highest Price | D7: =D4*C4 -> 80 | E7: 50
C8: Lower Price | D8: =C4-D7 -> 20 | E8: 20
D10: Total Profit | E10: =(D7*E7)+(D8*E8) -> 4400
C12: =E10 -> 4400
B13: 0.6 | C13: 3800
B14: 0.7 | C14: 4100
B15: 0.8 | C15: 4400
B16: 0.9 | C16: 4700
B17: 1 | C17: 5000

Sheet Data Table 2 var
B1: Book Store
C3: Total Number Of Books | D3: % Sold For The Highest Price
C4: 100 | D4: 0.7
D6: Number ofBooks | E6: UnitProfit
C7: HighestPrice | D7: =C4*D4 -> 70 | E7: 50
C8: Lower Price | D8: =C4-D7 -> 30 | E8: 20
D10: Total Profit | E10: =(D7*E7)+(D8*E8) -> 4100
B12: =E10 -> 4100 | C12: 50 | D12: 60 | E12: 70
B13: 0.6 | C13: 3800 | D13: 4400 | E13: 5000
B14: 0.7 | C14: 4100 | D14: 4800 | E14: 5500
B15: 0.8 | C15: 4400 | D15: 5200 | E15: 6000
B16: 0.9 | C16: 4700 | D16: 5600 | E16: 6500
B17: 1 | C17: 5000 | D17: 6000 | E17: 7000

Sheet Data Table-1 Var-Row
B2: Data tables are one of the existing parts of What-If analysis tools, which allow you to observe your result by experimenting it with different values of variables and to compare the outcomes stored by the data table.
B6: Loan Analysis | G6: Loan Amount
G7: 1500000 | H7: 2000000 | I7: 2500000 | J7: 3000000 | K7: 3500000 | L7: 4000000 | M7: 4500000 | N7: 5000000
B8: Interest Rate: | C8: 0.08 | F8: =C12 -> 28669.563 | G8: 14334.781 | H8: 19113.042 | I8: 23891.302 | J8: 28669.563 | K8: 33447.823 | L8: 38226.083 | M8: 43004.344 | N8: 47782.604
B9: Months of loan | C9: 180
B10: Loan Amount: | C10: 3000000
B11: Payments Due: | C11: 0
B12: Monthly Payment: | C12: =-PMT(C8/12,C9,C10,C11,0) -> 28669.563
B13: Total Payment: | C13: =C12*C9 -> 5160521.3
B14: Total Interest: | C14: =C13-C10 -> 2160521.3

Sheet Data Table-1 Var-Column
B2: Data tables are one of the existing parts of What-If analysis tools, which allow you to observe your result by experimenting it with different values of variables and to compare the outcomes stored by the data table.
B6: Loan Analysis | G6: Loan Amount
F7: =C12 -> 28669.563 | G7: 1500000 | H7: 2000000 | I7: 2500000 | J7: 3000000 | K7: 3500000 | L7: 4000000 | M7: 4500000 | N7: 5000000
B8: Interest Rate: | C8: 0.08 | E8: Rate of Interest | F8: 0.075 | G8: 13905.185 | H8: 18540.247 | I8: 23175.309 | J8: 27810.371 | K8: 32445.433 | L8: 37080.494 | M8: 41715.556 | N8: 46350.618
B9: Months of loan | C9: 180 | F9: 0.076 | G9: 13990.562 | H9: 18654.082 | I9: 23317.603 | J9: 27981.123 | K9: 32644.644 | L9: 37308.164 | M9: 41971.685 | N9: 46635.205
B10: Loan Amount: | C10: 3000000 | F10: 0.077 | G10: 14076.21 | H10: 18768.28 | I10: 23460.35 | J10: 28152.42 | K10: 32844.49 | L10: 37536.56 | M10: 42228.63 | N10: 46920.7
B11: Payments Due: | C11: 0 | F11: 0.078 | G11: 14162.13 | H11: 18882.84 | I11: 23603.55 | J11: 28324.26 | K11: 33044.971 | L11: 37765.681 | M11: 42486.391 | N11: 47207.101
B12: Monthly Payment: | C12: =-PMT(C8/12,C9,C10,C11,0) -> 28669.563 | F12: 0.079 | G12: 14248.321 | H12: 18997.761 | I12: 23747.202 | J12: 28496.642 | K12: 33246.082 | L12: 37995.523 | M12: 42744.963 | N12: 47494.403
B13: Total Payment: | C13: =C12*C9 -> 5160521.3 | F13: 0.08 | G13: 14334.781 | H13: 19113.042 | I13: 23891.302 | J13: 28669.563 | K13: 33447.823 | L13: 38226.083 | M13: 43004.344 | N13: 47782.604
B14: Total Interest: | C14: =C13-C10 -> 2160521.3 | F14: 0.081 | G14: 14421.51 | H14: 19228.68 | I14: 24035.85 | J14: 28843.021 | K14: 33650.191 | L14: 38457.361 | M14: 43264.531 | N14: 48071.701
F15: 0.082 | G15: 14508.507 | H15: 19344.676 | I15: 24180.845 | J15: 29017.014 | K15: 33853.183 | L15: 38689.352 | M15: 43525.521 | N15: 48361.69
F16: 0.083 | G16: 14595.77 | H16: 19461.027 | I16: 24326.284 | J16: 29191.541 | K16: 34056.797 | L16: 38922.054 | M16: 43787.311 | N16: 48652.568
F17: 0.084 | G17: 14683.299 | H17: 19577.733 | I17: 24472.166 | J17: 29366.599 | K17: 34261.032 | L17: 39155.465 | M17: 44049.898 | N17: 48944.332
F18: 0.085 | G18: 14771.093 | H18: 19694.791 | I18: 24618.489 | J18: 29542.187 | K18: 34465.885 | L18: 39389.582 | M18: 44313.28 | N18: 49236.978
F19: 0.086 | G19: 14859.151 | H19: 19812.201 | I19: 24765.252 | J19: 29718.302 | K19: 34671.352 | L19: 39624.403 | M19: 44577.453 | N19: 49530.503
F20: 0.087 | G20: 14947.471 | H20: 19929.962 | I20: 24912.452 | J20: 29894.943 | K20: 34877.433 | L20: 39859.924 | M20: 44842.414 | N20: 49824.905
F21: 0.088 | G21: 15036.053 | H21: 20048.071 | I21: 25060.089 | J21: 30072.107 | K21: 35084.125 | L21: 40096.143 | M21: 45108.16 | N21: 50120.178
F22: 0.089 | G22: 15124.896 | H22: 20166.528 | I22: 25208.16 | J22: 30249.793 | K22: 35291.425 | L22: 40333.057 | M22: 45374.689 | N22: 50416.321
F23: 0.09 | G23: 15213.999 | H23: 20285.332 | I23: 25356.665 | J23: 30427.998 | K23: 35499.33 | L23: 40570.663 | M23: 45641.996 | N23: 50713.329

Sheet Data Table 2
B2: Data tables are one of the existing parts of What-If analysis tools, which allow you to observe your result by experimenting it with different values of variables and to compare the outcomes stored by the data table.
B6: Loan Analysis | G6: Loan Amount
F7: =C12 -> 0 | G7: 1500000 | H7: 2000000 | I7: 2500000 | J7: 3000000 | K7: 3500000 | L7: 4000000 | M7: 4500000 | N7: 5000000
B8: Interest Rate: | C8: 0.08 | E8: Rate of Interest | F8: 0.075
B9: Months of loan | C9: 180 | F9: 0.076
B10: Loan Amount: | C10: 3000000 | F10: 0.077
B11: Payments Due: | C11: 0 | F11: 0.078
B12: Monthly Payment: | F12: 0.079
B13: Total Payment: | F13: 0.08
B14: Total Interest: | F14: 0.081
F15: 0.082
F16: 0.083
F17: 0.084
F18: 0.085
F19: 0.086
F20: 0.087
F21: 0.088
F22: 0.089
F23: 0.09

Sheet Solver
B2: Use Solver to find an optimal (maximum or minimum) value for a formula in one cell — called the objective cell — subject to constraints, or limits, on the values of other formula cells on a worksheet.
B12: Cost of Shipping Per Product
C13: Customer 1 | D13: Customer 2 | E13: Customer 3 | F13: Customer 4
B14: WareHouse1 | C14: 50 | D14: 65 | E14: 50 | F14: 90
B15: WareHouse2 | C15: 55 | D15: 70 | E15: 80 | F15: 75
B17: Number of Product Shipped
C18: Customer 1 | D18: Customer 2 | E18: Customer 3 | F18: Customer 4 | H18: Total Shipped | J18: Available in Warehouse
B19: WareHouse1 | C19: 32000 | D19: 0 | E19: 18000 | F19: 0 | H19: =SUM(C19:F19) -> 50000 | J19: 50000
B20: WareHouse2 | C20: 3000 | D20: 21000 | E20: 0 | F20: 33000 | H20: =SUM(C20:F20) -> 57000 | J20: 60000
B22: Total Received | C22: =SUM(C19:C20) -> 35000 | D22: =SUM(D19:D20) -> 21000 | E22: =SUM(E19:E20) -> 18000 | F22: =SUM(F19:F20) -> 33000
B23: Ordered | C23: 35000 | D23: 21000 | E23: 18000 | F23: 33000
B25: Total Shipping Cost | C25: =SUMPRODUCT(C14:F15,C19:F20) -> 6610000

Sheet Jan
A1: January Report
A3: Average of Monthly Gross Salary | B3: Mumbai | C3: Delhi | D3: Pune | E3: Nagpur | F3: Chennai | G3: Banglore
A4: Accounting | B4: 44000 | C4: 63014.667 | D4: 96110 | E4: 55828.667 | F4: 53278 | G4: 53274.333
A5: Business Development | B5: 71580.833 | C5: 53301.667 | D5: 76768.5 | E5: 68316.5 | F5: 64912.333 | G5: 101738.5
A6: Engineering | B6: 68228.8 | C6: 71992.25 | D6: 46774.667 | E6: 57441.667 | F6: 89982.167 | G6: 111181
A7: Human Resources | B7: 99555 | C7: 38930 | D7: 125835.29 | E7: 68348.714 | F7: 68549.714 | G7: 65911.333
A8: Legal | B8: 61826.8 | C8: 46426.25 | D8: 64245.25 | E8: 75779.5 | F8: 51527.75 | G8: 40834
A9: Marketing | B9: 123014.33 | C9: 43640.5 | D9: 48339.333 | E9: 53284.4 | F9: 69791.333 | G9: 152670.67
A10: Product Management | B10: 75382 | C10: 105891.14 | D10: 70183.75 | E10: 78184.333 | F10: 76775.8 | G10: 81244
A11: Research and Development | B11: 90331.6 | C11: 76744.333 | D11: 53212 | E11: 91280.333 | F11: 53268.5 | G11: 45260.25
A12: Sales | B12: 0 | C12: 72077.6 | D12: 53234.333 | E12: 116768.83 | F12: 38789.75 | G12: 71033.375
A13: Services | B13: 90042.2 | C13: 87655.2 | D13: 48094.167 | E13: 128191 | F13: 61102 | G13: 53291.5
A14: Support | B14: 142241.33 | C14: 67467 | D14: 53213.5 | E14: 118827.8 | F14: 121036 | G14: 54330.6
A15: Training | B15: 157682 | C15: 44431.8 | D15: 97265.5 | E15: 88315.429 | F15: 42113.333 | G15: 56045.8
A16: Grand Total | B16: =SUM(B4:B15) -> 1023884.9 | C16: =SUM(C4:C15) -> 771572.41 | D16: =SUM(D4:D15) -> 833276.29 | E16: =SUM(E4:E15) -> 1000567.2 | F16: =SUM(F4:F15) -> 791126.68 | G16: =SUM(G4:G15) -> 886815.36

Sheet Feb
A1: February Report
A3: Average of Monthly Gross Salary | B3: Mumbai | C3: Delhi | D3: Pune | E3: Nagpur | F3: Chennai | G3: Kota
A4: Sales | B4: 48968 | C4: 72077.6 | D4: 53234.333 | E4: 116768.83 | F4: 38789.75 | G4: 71033.375
A5: Accounting | B5: 53247 | C5: 63014.667 | D5: 96110 | E5: 55828.667 | F5: 53278 | G5: 53274.333
A6: Legal | B6: 61826.8 | C6: 46426.25 | D6: 64245.25 | E6: 75779.5 | F6: 51527.75 | G6: 40834
A7: Engineering | B7: 68228.8 | C7: 71992.25 | D7: 46774.667 | E7: 57441.667 | F7: 89982.167 | G7: 111181
A8: Business Development | B8: 71580.833 | C8: 53301.667 | D8: 76768.5 | E8: 68316.5 | F8: 64912.333 | G8: 101738.5
A9: Product Management | B9: 75382 | C9: 105891.14 | D9: 70183.75 | E9: 78184.333 | F9: 76775.8 | G9: 81244
A10: Services | B10: 90042.2 | C10: 87655.2 | D10: 48094.167 | E10: 128191 | F10: 61102 | G10: 53291.5
A11: Research and Development | B11: 90331.6 | C11: 76744.333 | D11: 53212 | E11: 91280.333 | F11: 53268.5 | G11: 45260.25
A12: Human Resources | B12: 99555 | C12: 38930 | D12: 125835.29 | E12: 68348.714 | F12: 68549.714 | G12: 65911.333
A13: Marketing | B13: 123014.33 | C13: 43640.5 | D13: 48339.333 | E13: 53284.4 | F13: 69791.333 | G13: 152670.67
A14: Support | B14: 142241.33 | C14: 67467 | D14: 53213.5 | E14: 118827.8 | F14: 121036 | G14: 54330.6
A15: Training | B15: 157682 | C15: 44431.8 | D15: 97265.5 | E15: 88315.429 | F15: 42113.333 | G15: 56045.8
A16: Grand Total | B16: =SUM(B4:B15) -> 1082099.9 | C16: =SUM(C4:C15) -> 771572.41 | D16: =SUM(D4:D15) -> 833276.29 | E16: =SUM(E4:E15) -> 1000567.2 | F16: =SUM(F4:F15) -> 791126.68 | G16: =SUM(G4:G15) -> 886815.36

Sheet Mar
A1: March Report
A3: Average of Monthly Gross Salary | B3: Hydrabad | C3: Delhi | D3: Pune | E3: Nagpur | F3: Chennai | G3: Banglore
A4: Marketing | B4: 123014.33 | C4: 43640.5 | D4: 48339.333 | E4: 53284.4 | F4: 69791.333 | G4: 152670.67
A5: Accounting | B5: 53247 | C5: 63014.667 | D5: 96110 | E5: 55828.667 | F5: 53278 | G5: 53274.333
A6: Engineering | B6: 68228.8 | C6: 71992.25 | D6: 46774.667 | E6: 57441.667 | F6: 89982.167 | G6: 111181
A7: Business Development | B7: 71580.833 | C7: 53301.667 | D7: 76768.5 | E7: 68316.5 | F7: 64912.333 | G7: 101738.5
A8: Human Resources | B8: 99555 | C8: 38930 | D8: 125835.29 | E8: 68348.714 | F8: 68549.714 | G8: 65911.333
A9: Legal | B9: 61826.8 | C9: 46426.25 | D9: 64245.25 | E9: 75779.5 | F9: 51527.75 | G9: 40834
A10: Product Management | B10: 75382 | C10: 105891.14 | D10: 70183.75 | E10: 78184.333 | F10: 76775.8 | G10: 81244
A11: Training | B11: 157682 | C11: 44431.8 | D11: 97265.5 | E11: 88315.429 | F11: 42113.333 | G11: 56045.8
A12: Research and Development | B12: 90331.6 | C12: 76744.333 | D12: 53212 | E12: 91280.333 | F12: 53268.5 | G12: 45260.25
A13: Sales | B13: 48968 | C13: 72077.6 | D13: 53234.333 | E13: 116768.83 | F13: 38789.75 | G13: 71033.375
A14: Services | B14: 90042.2 | C14: 87655.2 | D14: 48094.167 | E14: 128191 | F14: 61102 | G14: 53291.5
A15: Grand Total | B15: =SUM(B4:B14) -> 939858.57 | C15: =SUM(C4:C14) -> 704105.41 | D15: =SUM(D4:D14) -> 780062.79 | E15: =SUM(E4:E14) -> 881739.38 | F15: =SUM(F4:F14) -> 670090.68 | G15: =SUM(G4:G14) -> 832484.76

Sheet Expected Report
A1: Qrt1 Report
A3: Average of Monthly Gross Salary | D3: Mumbai | E3: Hydrabad | F3: Delhi | G3: Pune | H3: Nagpur | I3: Chennai | J3: Kota | K3: Banglore
A4: Sales | D4: 97936 | E4: 48968 | F4: 216232.8 | G4: 159703 | H4: 350306.5 | I4: 116369.25 | J4: 71033.375 | K4: 142066.75
A5: Accounting | D5: 106494 | E5: 53247 | F5: 189044 | G5: 288330 | H5: 167486 | I5: 159834 | J5: 53274.333 | K5: 106548.67
A6: Legal | D6: 123653.6 | E6: 61826.8 | F6: 139278.75 | G6: 192735.75 | H6: 227338.5 | I6: 154583.25 | J6: 40834 | K6: 81668
A7: Engineering | D7: 136457.6 | E7: 68228.8 | F7: 215976.75 | G7: 140324 | H7: 172325 | I7: 269946.5 | J7: 111181 | K7: 222362
A8: Business Development | D8: 143161.67 | E8: 71580.833 | F8: 159905 | G8: 230305.5 | H8: 204949.5 | I8: 194737 | J8: 101738.5 | K8: 203477
A9: Product Management | D9: 150764 | E9: 75382 | F9: 317673.43 | G9: 210551.25 | H9: 234553 | I9: 230327.4 | J9: 81244 | K9: 162488
A10: Services | D10: 180084.4 | E10: 90042.2 | F10: 262965.6 | G10: 144282.5 | H10: 384573 | I10: 183306 | J10: 53291.5 | K10: 106583
A11: Research and Development | D11: 180663.2 | E11: 90331.6 | F11: 230233 | G11: 159636 | H11: 273841 | I11: 159805.5 | J11: 45260.25 | K11: 90520.5
A12: Human Resources | D12: 199110 | E12: 99555 | F12: 116790 | G12: 377505.86 | H12: 205046.14 | I12: 205649.14 | J12: 65911.333 | K12: 131822.67
A13: Marketing | D13: 246028.67 | E13: 123014.33 | F13: 130921.5 | G13: 145018 | H13: 159853.2 | I13: 209374 | J13: 152670.67 | K13: 305341.33
A14: Support | D14: 284482.67 | F14: 134934 | G14: 106427 | H14: 237655.6 | I14: 242072 | J14: 54330.6 | K14: 54330.6
A15: Training | D15: 315364 | E15: 157682 | F15: 133295.4 | G15: 291796.5 | H15: 264946.29 | I15: 126340 | J15: 56045.8 | K15: 112091.6
A16: Grand Total | D16: 2164199.8 | E16: 939858.57 | F16: 2247250.2 | G16: 2446615.4 | H16: 2882873.7 | I16: 2252344 | J16: 886815.36 | K16: 1719300.1
A19: Average of Monthly Gross Salary | C19: Mumbai | D19: Hydrabad | E19: Delhi | F19: Pune | G19: Nagpur | H19: Chennai | I19: Kota | J19: Banglore
C20: =Feb!$B$4 -> 48968 | E20: =Feb!$C$4 -> 72077.6 | F20: =Feb!$D$4 -> 53234.333 | G20: =Feb!$E$4 -> 116768.83 | H20: =Feb!$F$4 -> 38789.75 | I20: =Feb!$G$4 -> 71033.375
C21: =Jan!$B$12 -> 0 | E21: =Jan!$C$12 -> 72077.6 | F21: =Jan!$D$12 -> 53234.333 | G21: =Jan!$E$12 -> 116768.83 | H21: =Jan!$F$12 -> 38789.75 | J21: =Jan!$G$12 -> 71033.375
D22: =Mar!$B$13 -> 48968 | E22: =Mar!$C$13 -> 72077.6 | F22: =Mar!$D$13 -> 53234.333 | G22: =Mar!$E$13 -> 116768.83 | H22: =Mar!$F$13 -> 38789.75 | J22: =Mar!$G$13 -> 71033.375
A23: Sales | C23: =SUM(C20:C22) -> 48968 | D23: =SUM(D20:D22) -> 48968 | E23: =SUM(E20:E22) -> 216232.8 | F23: =SUM(F20:F22) -> 159703 | G23: =SUM(G20:G22) -> 350306.5 | H23: =SUM(H20:H22) -> 116369.25 | I23: =SUM(I20:I22) -> 71033.375 | J23: =SUM(J20:J22) -> 142066.75
C24: =Feb!$B$5 -> 53247 | E24: =Feb!$C$5 -> 63014.667 | F24: =Feb!$D$5 -> 96110 | G24: =Feb!$E$5 -> 55828.667 | H24: =Feb!$F$5 -> 53278 | I24: =Feb!$G$5 -> 53274.333
C25: =Jan!$B$4 -> 44000 | E25: =Jan!$C$4 -> 63014.667 | F25: =Jan!$D$4 -> 96110 | G25: =Jan!$E$4 -> 55828.667 | H25: =Jan!$F$4 -> 53278 | J25: =Jan!$G$4 -> 53274.333
D26: =Mar!$B$5 -> 53247 | E26: =Mar!$C$5 -> 63014.667 | F26: =Mar!$D$5 -> 96110 | G26: =Mar!$E$5 -> 55828.667 | H26: =Mar!$F$5 -> 53278 | J26: =Mar!$G$5 -> 53274.333
A27: Accounting | C27: =SUM(C24:C26) -> 97247 | D27: =SUM(D24:D26) -> 53247 | E27: =SUM(E24:E26) -> 189044 | F27: =SUM(F24:F26) -> 288330 | G27: =SUM(G24:G26) -> 167486 | H27: =SUM(H24:H26) -> 159834 | I27: =SUM(I24:I26) -> 53274.333 | J27: =SUM(J24:J26) -> 106548.67
C28: =Feb!$B$6 -> 61826.8 | E28: =Feb!$C$6 -> 46426.25 | F28: =Feb!$D$6 -> 64245.25 | G28: =Feb!$E$6 -> 75779.5 | H28: =Feb!$F$6 -> 51527.75 | I28: =Feb!$G$6 -> 40834
C29: =Jan!$B$8 -> 61826.8 | E29: =Jan!$C$8 -> 46426.25 | F29: =Jan!$D$8 -> 64245.25 | G29: =Jan!$E$8 -> 75779.5 | H29: =Jan!$F$8 -> 51527.75 | J29: =Jan!$G$8 -> 40834
D30: =Mar!$B$9 -> 61826.8 | E30: =Mar!$C$9 -> 46426.25 | F30: =Mar!$D$9 -> 64245.25 | G30: =Mar!$E$9 -> 75779.5 | H30: =Mar!$F$9 -> 51527.75 | J30: =Mar!$G$9 -> 40834
A31: Legal | C31: =SUM(C28:C30) -> 123653.6 | D31: =SUM(D28:D30) -> 61826.8 | E31: =SUM(E28:E30) -> 139278.75 | F31: =SUM(F28:F30) -> 192735.75 | G31: =SUM(G28:G30) -> 227338.5 | H31: =SUM(H28:H30) -> 154583.25 | I31: =SUM(I28:I30) -> 40834 | J31: =SUM(J28:J30) -> 81668
C32: =Feb!$B$7 -> 68228.8 | E32: =Feb!$C$7 -> 71992.25 | F32: =Feb!$D$7 -> 46774.667 | G32: =Feb!$E$7 -> 57441.667 | H32: =Feb!$F$7 -> 89982.167 | I32: =Feb!$G$7 -> 111181
C33: =Jan!$B$6 -> 68228.8 | E33: =Jan!$C$6 -> 71992.25 | F33: =Jan!$D$6 -> 46774.667 | G33: =Jan!$E$6 -> 57441.667 | H33: =Jan!$F$6 -> 89982.167 | J33: =Jan!$G$6 -> 111181
D34: =Mar!$B$6 -> 68228.8 | E34: =Mar!$C$6 -> 71992.25 | F34: =Mar!$D$6 -> 46774.667 | G34: =Mar!$E$6 -> 57441.667 | H34: =Mar!$F$6 -> 89982.167 | J34: =Mar!$G$6 -> 111181
A35: Engineering | C35: =SUM(C32:C34) -> 136457.6 | D35: =SUM(D32:D34) -> 68228.8 | E35: =SUM(E32:E34) -> 215976.75 | F35: =SUM(F32:F34) -> 140324 | G35: =SUM(G32:G34) -> 172325 | H35: =SUM(H32:H34) -> 269946.5 | I35: =SUM(I32:I34) -> 111181 | J35: =SUM(J32:J34) -> 222362
C36: =Feb!$B$8 -> 71580.833 | E36: =Feb!$C$8 -> 53301.667 | F36: =Feb!$D$8 -> 76768.5 | G36: =Feb!$E$8 -> 68316.5 | H36: =Feb!$F$8 -> 64912.333 | I36: =Feb!$G$8 -> 101738.5
C37: =Jan!$B$5 -> 71580.833 | E37: =Jan!$C$5 -> 53301.667 | F37: =Jan!$D$5 -> 76768.5 | G37: =Jan!$E$5 -> 68316.5 | H37: =Jan!$F$5 -> 64912.333 | J37: =Jan!$G$5 -> 101738.5
D38: =Mar!$B$7 -> 71580.833 | E38: =Mar!$C$7 -> 53301.667 | F38: =Mar!$D$7 -> 76768.5 | G38: =Mar!$E$7 -> 68316.5 | H38: =Mar!$F$7 -> 64912.333 | J38: =Mar!$G$7 -> 101738.5
A39: Business Development | C39: =SUM(C36:C38) -> 143161.67 | D39: =SUM(D36:D38) -> 71580.833 | E39: =SUM(E36:E38) -> 159905 | F39: =SUM(F36:F38) -> 230305.5 | G39: =SUM(G36:G38) -> 204949.5 | H39: =SUM(H36:H38) -> 194737 | I39: =SUM(I36:I38) -> 101738.5 | J39: =SUM(J36:J38) -> 203477
C40: =Feb!$B$9 -> 75382 | E40: =Feb!$C$9 -> 105891.14 | F40: =Feb!$D$9 -> 70183.75 | G40: =Feb!$E$9 -> 78184.333 | H40: =Feb!$F$9 -> 76775.8 | I40: =Feb!$G$9 -> 81244
C41: =Jan!$B$10 -> 75382 | E41: =Jan!$C$10 -> 105891.14 | F41: =Jan!$D$10 -> 70183.75 | G41: =Jan!$E$10 -> 78184.333 | H41: =Jan!$F$10 -> 76775.8 | J41: =Jan!$G$10 -> 81244
D42: =Mar!$B$10 -> 75382 | E42: =Mar!$C$10 -> 105891.14 | F42: =Mar!$D$10 -> 70183.75 | G42: =Mar!$E$10 -> 78184.333 | H42: =Mar!$F$10 -> 76775.8 | J42: =Mar!$G$10 -> 81244
A43: Product Management | C43: =SUM(C40:C42) -> 150764 | D43: =SUM(D40:D42) -> 75382 | E43: =SUM(E40:E42) -> 317673.43 | F43: =SUM(F40:F42) -> 210551.25 | G43: =SUM(G40:G42) -> 234553 | H43: =SUM(H40:H42) -> 230327.4 | I43: =SUM(I40:I42) -> 81244 | J43: =SUM(J40:J42) -> 162488
C44: =Feb!$B$10 -> 90042.2 | E44: =Feb!$C$10 -> 87655.2 | F44: =Feb!$D$10 -> 48094.167 | G44: =Feb!$E$10 -> 128191 | H44: =Feb!$F$10 -> 61102 | I44: =Feb!$G$10 -> 53291.5
C45: =Jan!$B$13 -> 90042.2 | E45: =Jan!$C$13 -> 87655.2 | F45: =Jan!$D$13 -> 48094.167 | G45: =Jan!$E$13 -> 128191 | H45: =Jan!$F$13 -> 61102 | J45: =Jan!$G$13 -> 53291.5
D46: =Mar!$B$14 -> 90042.2 | E46: =Mar!$C$14 -> 87655.2 | F46: =Mar!$D$14 -> 48094.167 | G46: =Mar!$E$14 -> 128191 | H46: =Mar!$F$14 -> 61102 | J46: =Mar!$G$14 -> 53291.5
A47: Services | C47: =SUM(C44:C46) -> 180084.4 | D47: =SUM(D44:D46) -> 90042.2 | E47: =SUM(E44:E46) -> 262965.6 | F47: =SUM(F44:F46) -> 144282.5 | G47: =SUM(G44:G46) -> 384573 | H47: =SUM(H44:H46) -> 183306 | I47: =SUM(I44:I46) -> 53291.5 | J47: =SUM(J44:J46) -> 106583
C48: =Feb!$B$11 -> 90331.6 | E48: =Feb!$C$11 -> 76744.333 | F48: =Feb!$D$11 -> 53212 | G48: =Feb!$E$11 -> 91280.333 | H48: =Feb!$F$11 -> 53268.5 | I48: =Feb!$G$11 -> 45260.25
C49: =Jan!$B$11 -> 90331.6 | E49: =Jan!$C$11 -> 76744.333 | F49: =Jan!$D$11 -> 53212 | G49: =Jan!$E$11 -> 91280.333 | H49: =Jan!$F$11 -> 53268.5 | J49: =Jan!$G$11 -> 45260.25
D50: =Mar!$B$12 -> 90331.6 | E50: =Mar!$C$12 -> 76744.333 | F50: =Mar!$D$12 -> 53212 | G50: =Mar!$E$12 -> 91280.333 | H50: =Mar!$F$12 -> 53268.5 | J50: =Mar!$G$12 -> 45260.25
A51: Research and Development | C51: =SUM(C48:C50) -> 180663.2 | D51: =SUM(D48:D50) -> 90331.6 | E51: =SUM(E48:E50) -> 230233 | F51: =SUM(F48:F50) -> 159636 | G51: =SUM(G48:G50) -> 273841 | H51: =SUM(H48:H50) -> 159805.5 | I51: =SUM(I48:I50) -> 45260.25 | J51: =SUM(J48:J50) -> 90520.5
C52: =Feb!$B$12 -> 99555 | E52: =Feb!$C$12 -> 38930 | F52: =Feb!$D$12 -> 125835.29 | G52: =Feb!$E$12 -> 68348.714 | H52: =Feb!$F$12 -> 68549.714 | I52: =Feb!$G$12 -> 65911.333
C53: =Jan!$B$7 -> 99555 | E53: =Jan!$C$7 -> 38930 | F53: =Jan!$D$7 -> 125835.29 | G53: =Jan!$E$7 -> 68348.714 | H53: =Jan!$F$7 -> 68549.714 | J53: =Jan!$G$7 -> 65911.333
D54: =Mar!$B$8 -> 99555 | E54: =Mar!$C$8 -> 38930 | F54: =Mar!$D$8 -> 125835.29 | G54: =Mar!$E$8 -> 68348.714 | H54: =Mar!$F$8 -> 68549.714 | J54: =Mar!$G$8 -> 65911.333
A55: Human Resources | C55: =SUM(C52:C54) -> 199110 | D55: =SUM(D52:D54) -> 99555 | E55: =SUM(E52:E54) -> 116790 | F55: =SUM(F52:F54) -> 377505.86 | G55: =SUM(G52:G54) -> 205046.14 | H55: =SUM(H52:H54) -> 205649.14 | I55: =SUM(I52:I54) -> 65911.333 | J55: =SUM(J52:J54) -> 131822.67
C56: =Feb!$B$13 -> 123014.33 | E56: =Feb!$C$13 -> 43640.5 | F56: =Feb!$D$13 -> 48339.333 | G56: =Feb!$E$13 -> 53284.4 | H56: =Feb!$F$13 -> 69791.333 | I56: =Feb!$G$13 -> 152670.67
C57: =Jan!$B$9 -> 123014.33 | E57: =Jan!$C$9 -> 43640.5 | F57: =Jan!$D$9 -> 48339.333 | G57: =Jan!$E$9 -> 53284.4 | H57: =Jan!$F$9 -> 69791.333 | J57: =Jan!$G$9 -> 152670.67
D58: =Mar!$B$4 -> 123014.33 | E58: =Mar!$C$4 -> 43640.5 | F58: =Mar!$D$4 -> 48339.333 | G58: =Mar!$E$4 -> 53284.4 | H58: =Mar!$F$4 -> 69791.333 | J58: =Mar!$G$4 -> 152670.67
A59: Marketing | C59: =SUM(C56:C58) -> 246028.67 | D59: =SUM(D56:D58) -> 123014.33 | E59: =SUM(E56:E58) -> 130921.5 | F59: =SUM(F56:F58) -> 145018 | G59: =SUM(G56:G58) -> 159853.2 | H59: =SUM(H56:H58) -> 209374 | I59: =SUM(I56:I58) -> 152670.67 | J59: =SUM(J56:J58) -> 305341.33
C60: =Feb!$B$14 -> 142241.33 | E60: =Feb!$C$14 -> 67467 | F60: =Feb!$D$14 -> 53213.5 | G60: =Feb!$E$14 -> 118827.8 | H60: =Feb!$F$14 -> 121036 | I60: =Feb!$G$14 -> 54330.6
C61: =Jan!$B$14 -> 142241.33 | E61: =Jan!$C$14 -> 67467 | F61: =Jan!$D$14 -> 53213.5 | G61: =Jan!$E$14 -> 118827.8 | H61: =Jan!$F$14 -> 121036 | J61: =Jan!$G$14 -> 54330.6
A62: Support | C62: =SUM(C60:C61) -> 284482.67 | E62: =SUM(E60:E61) -> 134934 | F62: =SUM(F60:F61) -> 106427 | G62: =SUM(G60:G61) -> 237655.6 | H62: =SUM(H60:H61) -> 242072 | I62: =SUM(I60:I61) -> 54330.6 | J62: =SUM(J60:J61) -> 54330.6
C63: =Feb!$B$15 -> 157682 | E63: =Feb!$C$15 -> 44431.8 | F63: =Feb!$D$15 -> 97265.5 | G63: =Feb!$E$15 -> 88315.429 | H63: =Feb!$F$15 -> 42113.333 | I63: =Feb!$G$15 -> 56045.8
C64: =Jan!$B$15 -> 157682 | E64: =Jan!$C$15 -> 44431.8 | F64: =Jan!$D$15 -> 97265.5 | G64: =Jan!$E$15 -> 88315.429 | H64: =Jan!$F$15 -> 42113.333 | J64: =Jan!$G$15 -> 56045.8
D65: =Mar!$B$11 -> 157682 | E65: =Mar!$C$11 -> 44431.8 | F65: =Mar!$D$11 -> 97265.5 | G65: =Mar!$E$11 -> 88315.429 | H65: =Mar!$F$11 -> 42113.333 | J65: =Mar!$G$11 -> 56045.8
A66: Training | C66: =SUM(C63:C65) -> 315364 | D66: =SUM(D63:D65) -> 157682 | E66: =SUM(E63:E65) -> 133295.4 | F66: =SUM(F63:F65) -> 291796.5 | G66: =SUM(G63:G65) -> 264946.29 | H66: =SUM(H63:H65) -> 126340 | I66: =SUM(I63:I65) -> 56045.8 | J66: =SUM(J63:J65) -> 112091.6
A67: Grand Total | C67: 2105984.8 | D67: 939858.57 | E67: 2247250.2 | F67: 2446615.4 | G67: 2882873.7 | H67: 2252344 | I67: 886815.36 | J67: 1719300
C70: Mumbai | D70: Hydrabad | E70: Delhi | F70: Pune | G70: Nagpur | H70: Chennai | I70: Kota | J70: Banglore
B71: Module8-The Data Tab | C71: =Feb!$B$4 -> 48968 | E71: =Feb!$C$4 -> 72077.6 | F71: =Feb!$D$4 -> 53234.333 | G71: =Feb!$E$4 -> 116768.83 | H71: =Feb!$F$4 -> 38789.75 | I71: =Feb!$G$4 -> 71033.375
B72: Module8-The Data Tab | C72: =Jan!$B$12 -> 0 | E72: =Jan!$C$12 -> 72077.6 | F72: =Jan!$D$12 -> 53234.333 | G72: =Jan!$E$12 -> 116768.83 | H72: =Jan!$F$12 -> 38789.75 | J72: =Jan!$G$12 -> 71033.375
B73: Module8-The Data Tab | D73: =Mar!$B$13 -> 48968 | E73: =Mar!$C$13 -> 72077.6 | F73: =Mar!$D$13 -> 53234.333 | G73: =Mar!$E$13 -> 116768.83 | H73: =Mar!$F$13 -> 38789.75 | J73: =Mar!$G$13 -> 71033.375
A74: Sales | C74: =SUM(C71:C73) -> 48968 | D74: =SUM(D71:D73) -> 48968 | E74: =SUM(E71:E73) -> 216232.8 | F74: =SUM(F71:F73) -> 159703 | G74: =SUM(G71:G73) -> 350306.5 | H74: =SUM(H71:H73) -> 116369.25 | I74: =SUM(I71:I73) -> 71033.375 | J74: =SUM(J71:J73) -> 142066.75
B75: Module8-The Data Tab | C75: =Feb!$B$5 -> 53247 | E75: =Feb!$C$5 -> 63014.667 | F75: =Feb!$D$5 -> 96110 | G75: =Feb!$E$5 -> 55828.667 | H75: =Feb!$F$5 -> 53278 | I75: =Feb!$G$5 -> 53274.333
B76: Module8-The Data Tab | C76: =Jan!$B$4 -> 44000 | E76: =Jan!$C$4 -> 63014.667 | F76: =Jan!$D$4 -> 96110 | G76: =Jan!$E$4 -> 55828.667 | H76: =Jan!$F$4 -> 53278 | J76: =Jan!$G$4 -> 53274.333
B77: Module8-The Data Tab | D77: =Mar!$B$5 -> 53247 | E77: =Mar!$C$5 -> 63014.667 | F77: =Mar!$D$5 -> 96110 | G77: =Mar!$E$5 -> 55828.667 | H77: =Mar!$F$5 -> 53278 | J77: =Mar!$G$5 -> 53274.333
A78: Accounting | C78: =SUM(C75:C77) -> 97247 | D78: =SUM(D75:D77) -> 53247 | E78: =SUM(E75:E77) -> 189044 | F78: =SUM(F75:F77) -> 288330 | G78: =SUM(G75:G77) -> 167486 | H78: =SUM(H75:H77) -> 159834 | I78: =SUM(I75:I77) -> 53274.333 | J78: =SUM(J75:J77) -> 106548.67
B79: Module8-The Data Tab | C79: =Feb!$B$6 -> 61826.8 | E79: =Feb!$C$6 -> 46426.25 | F79: =Feb!$D$6 -> 64245.25 | G79: =Feb!$E$6 -> 75779.5 | H79: =Feb!$F$6 -> 51527.75 | I79: =Feb!$G$6 -> 40834
B80: Module8-The Data Tab | C80: =Jan!$B$8 -> 61826.8 | E80: =Jan!$C$8 -> 46426.25 | F80: =Jan!$D$8 -> 64245.25 | G80: =Jan!$E$8 -> 75779.5 | H80: =Jan!$F$8 -> 51527.75 | J80: =Jan!$G$8 -> 40834
B81: Module8-The Data Tab | D81: =Mar!$B$9 -> 61826.8 | E81: =Mar!$C$9 -> 46426.25 | F81: =Mar!$D$9 -> 64245.25 | G81: =Mar!$E$9 -> 75779.5 | H81: =Mar!$F$9 -> 51527.75 | J81: =Mar!$G$9 -> 40834
A82: Legal | C82: =SUM(C79:C81) -> 123653.6 | D82: =SUM(D79:D81) -> 61826.8 | E82: =SUM(E79:E81) -> 139278.75 | F82: =SUM(F79:F81) -> 192735.75 | G82: =SUM(G79:G81) -> 227338.5 | H82: =SUM(H79:H81) -> 154583.25 | I82: =SUM(I79:I81) -> 40834 | J82: =SUM(J79:J81) -> 81668
B83: Module8-The Data Tab | C83: =Feb!$B$7 -> 68228.8 | E83: =Feb!$C$7 -> 71992.25 | F83: =Feb!$D$7 -> 46774.667 | G83: =Feb!$E$7 -> 57441.667 | H83: =Feb!$F$7 -> 89982.167 | I83: =Feb!$G$7 -> 111181
B84: Module8-The Data Tab | C84: =Jan!$B$6 -> 68228.8 | E84: =Jan!$C$6 -> 71992.25 | F84: =Jan!$D$6 -> 46774.667 | G84: =Jan!$E$6 -> 57441.667 | H84: =Jan!$F$6 -> 89982.167 | J84: =Jan!$G$6 -> 111181
B85: Module8-The Data Tab | D85: =Mar!$B$6 -> 68228.8 | E85: =Mar!$C$6 -> 71992.25 | F85: =Mar!$D$6 -> 46774.667 | G85: =Mar!$E$6 -> 57441.667 | H85: =Mar!$F$6 -> 89982.167 | J85: =Mar!$G$6 -> 111181
A86: Engineering | C86: =SUM(C83:C85) -> 136457.6 | D86: =SUM(D83:D85) -> 68228.8 | E86: =SUM(E83:E85) -> 215976.75 | F86: =SUM(F83:F85) -> 140324 | G86: =SUM(G83:G85) -> 172325 | H86: =SUM(H83:H85) -> 269946.5 | I86: =SUM(I83:I85) -> 111181 | J86: =SUM(J83:J85) -> 222362
B87: Module8-The Data Tab | C87: =Feb!$B$8 -> 71580.833 | E87: =Feb!$C$8 -> 53301.667 | F87: =Feb!$D$8 -> 76768.5 | G87: =Feb!$E$8 -> 68316.5 | H87: =Feb!$F$8 -> 64912.333 | I87: =Feb!$G$8 -> 101738.5
B88: Module8-The Data Tab | C88: =Jan!$B$5 -> 71580.833 | E88: =Jan!$C$5 -> 53301.667 | F88: =Jan!$D$5 -> 76768.5 | G88: =Jan!$E$5 -> 68316.5 | H88: =Jan!$F$5 -> 64912.333 | J88: =Jan!$G$5 -> 101738.5
B89: Module8-The Data Tab | D89: =Mar!$B$7 -> 71580.833 | E89: =Mar!$C$7 -> 53301.667 | F89: =Mar!$D$7 -> 76768.5 | G89: =Mar!$E$7 -> 68316.5 | H89: =Mar!$F$7 -> 64912.333 | J89: =Mar!$G$7 -> 101738.5
A90: Business Development | C90: =SUM(C87:C89) -> 143161.67 | D90: =SUM(D87:D89) -> 71580.833 | E90: =SUM(E87:E89) -> 159905 | F90: =SUM(F87:F89) -> 230305.5 | G90: =SUM(G87:G89) -> 204949.5 | H90: =SUM(H87:H89) -> 194737 | I90: =SUM(I87:I89) -> 101738.5 | J90: =SUM(J87:J89) -> 203477
B91: Module8-The Data Tab | C91: =Feb!$B$9 -> 75382 | E91: =Feb!$C$9 -> 105891.14 | F91: =Feb!$D$9 -> 70183.75 | G91: =Feb!$E$9 -> 78184.333 | H91: =Feb!$F$9 -> 76775.8 | I91: =Feb!$G$9 -> 81244
B92: Module8-The Data Tab | C92: =Jan!$B$10 -> 75382 | E92: =Jan!$C$10 -> 105891.14 | F92: =Jan!$D$10 -> 70183.75 | G92: =Jan!$E$10 -> 78184.333 | H92: =Jan!$F$10 -> 76775.8 | J92: =Jan!$G$10 -> 81244
B93: Module8-The Data Tab | D93: =Mar!$B$10 -> 75382 | E93: =Mar!$C$10 -> 105891.14 | F93: =Mar!$D$10 -> 70183.75 | G93: =Mar!$E$10 -> 78184.333 | H93: =Mar!$F$10 -> 76775.8 | J93: =Mar!$G$10 -> 81244
A94: Product Management | C94: =SUM(C91:C93) -> 150764 | D94: =SUM(D91:D93) -> 75382 | E94: =SUM(E91:E93) -> 317673.43 | F94: =SUM(F91:F93) -> 210551.25 | G94: =SUM(G91:G93) -> 234553 | H94: =SUM(H91:H93) -> 230327.4 | I94: =SUM(I91:I93) -> 81244 | J94: =SUM(J91:J93) -> 162488
B95: Module8-The Data Tab | C95: =Feb!$B$10 -> 90042.2 | E95: =Feb!$C$10 -> 87655.2 | F95: =Feb!$D$10 -> 48094.167 | G95: =Feb!$E$10 -> 128191 | H95: =Feb!$F$10 -> 61102 | I95: =Feb!$G$10 -> 53291.5
B96: Module8-The Data Tab | C96: =Jan!$B$13 -> 90042.2 | E96: =Jan!$C$13 -> 87655.2 | F96: =Jan!$D$13 -> 48094.167 | G96: =Jan!$E$13 -> 128191 | H96: =Jan!$F$13 -> 61102 | J96: =Jan!$G$13 -> 53291.5
B97: Module8-The Data Tab | D97: =Mar!$B$14 -> 90042.2 | E97: =Mar!$C$14 -> 87655.2 | F97: =Mar!$D$14 -> 48094.167 | G97: =Mar!$E$14 -> 128191 | H97: =Mar!$F$14 -> 61102 | J97: =Mar!$G$14 -> 53291.5
A98: Services | C98: =SUM(C95:C97) -> 180084.4 | D98: =SUM(D95:D97) -> 90042.2 | E98: =SUM(E95:E97) -> 262965.6 | F98: =SUM(F95:F97) -> 144282.5 | G98: =SUM(G95:G97) -> 384573 | H98: =SUM(H95:H97) -> 183306 | I98: =SUM(I95:I97) -> 53291.5 | J98: =SUM(J95:J97) -> 106583
B99: Module8-The Data Tab | C99: =Feb!$B$11 -> 90331.6 | E99: =Feb!$C$11 -> 76744.333 | F99: =Feb!$D$11 -> 53212 | G99: =Feb!$E$11 -> 91280.333 | H99: =Feb!$F$11 -> 53268.5 | I99: =Feb!$G$11 -> 45260.25
B100: Module8-The Data Tab | C100: =Jan!$B$11 -> 90331.6 | E100: =Jan!$C$11 -> 76744.333 | F100: =Jan!$D$11 -> 53212 | G100: =Jan!$E$11 -> 91280.333 | H100: =Jan!$F$11 -> 53268.5 | J100: =Jan!$G$11 -> 45260.25
B101: Module8-The Data Tab | D101: =Mar!$B$12 -> 90331.6 | E101: =Mar!$C$12 -> 76744.333 | F101: =Mar!$D$12 -> 53212 | G101: =Mar!$E$12 -> 91280.333 | H101: =Mar!$F$12 -> 53268.5 | J101: =Mar!$G$12 -> 45260.25
A102: Research and Development | C102: =SUM(C99:C101) -> 180663.2 | D102: =SUM(D99:D101) -> 90331.6 | E102: =SUM(E99:E101) -> 230233 | F102: =SUM(F99:F101) -> 159636 | G102: =SUM(G99:G101) -> 273841 | H102: =SUM(H99:H101) -> 159805.5 | I102: =SUM(I99:I101) -> 45260.25 | J102: =SUM(J99:J101) -> 90520.5
B103: Module8-The Data Tab | C103: =Feb!$B$12 -> 99555 | E103: =Feb!$C$12 -> 38930 | F103: =Feb!$D$12 -> 125835.29 | G103: =Feb!$E$12 -> 68348.714 | H103: =Feb!$F$12 -> 68549.714 | I103: =Feb!$G$12 -> 65911.333
B104: Module8-The Data Tab | C104: =Jan!$B$7 -> 99555 | E104: =Jan!$C$7 -> 38930 | F104: =Jan!$D$7 -> 125835.29 | G104: =Jan!$E$7 -> 68348.714 | H104: =Jan!$F$7 -> 68549.714 | J104: =Jan!$G$7 -> 65911.333
B105: Module8-The Data Tab | D105: =Mar!$B$8 -> 99555 | E105: =Mar!$C$8 -> 38930 | F105: =Mar!$D$8 -> 125835.29 | G105: =Mar!$E$8 -> 68348.714 | H105: =Mar!$F$8 -> 68549.714 | J105: =Mar!$G$8 -> 65911.333
...

Sheet Data Validation
A1: Ex.1 | B1: Allow any whole number between 0 to 100
B3: 3
B4: 0
B5: 100
A7: Ex.2 | B7: Allow any value between 0 to 100 with decimals
B9: 0.5
B10: 15
B11: 12
A13: Ex.3 | B13: Allow any value between 0 to 100 with input message as "Please Enter any value between 0 to 100"
B15: 100
B16: 0.556
B17: 11.789
A19: Ex.4 | B19: Error Alert
B20: Enter any whole number between 0 to 100
B22: 0
B23: 100
B24: 20
A26: Ex.5 | B26: Create a list from range E28:E29
B28: Student | C28: Attendance | E28: Yes | F28: Data validation list
B29: Gitesh | C29: Yes | E29: No
B30: Mahesh | C30: No
B31: Melvin | C31: Yes
B32: Neelesh | C32: Yes
B33: Kishor | C33: No
B34: Ashish | C34: No
A37: Ex.6 | B37: Create a validation list so that user can only enter dates between 1st Apr 2019 and 31st Mar.2020
B39: 43586
B40: 43742 | C40: 43791 | D40: 43852
B41: 43921
A45: Ex.7 | B45: Validate cell show that the duplicate values are not allowed
B46: 1 | C46: Muskan | D46: Roshni
B47: 2 | C47: 13 | D47: Kanchan
B48: 3 | C48: 31 | D48: Deepak
A50: Ex.8 | B50: Validate cells so that first three characters are "EMP"
B52: emp123 | C52: =LEFT(B52,3)="EMP" -> TRUE | D52: =LEN(B52)=6 -> TRUE | E52: =AND(LEFT(B52,3)="EMP",LEN(B52)=6) -> TRUE
B53: emp155 | D53: =AND(C52:D52) -> TRUE
B54: emp267
B55: emp100
B56: emp100 | D56: Here duplicates can also be rejected by writing COUNTIF() in AND()
D57: to remove duplicate emp id
A58: Ex.9 | B58: Validate cells so that only phone numbers are allowed in the below cells
B60: 8103123456 | E60: =AND(ISNUMBER(B60),LEN(B60)=10) -> TRUE | F60: If we want to more restrict it as we want
B61: 1234567890 | F61: indian number starts with 91 LEFT(B60,2)="91"
B62: 9876543210
B63: 9876123450
A66: Ex.10 | B66: Validate cells so that only date below todays date is allowed in the below cells
B68: 46033
B69: 46014
B70: 37560
B71: 23835
A74: Ex.11 | F74: Select Header | H74: dependant list
B75: Vegetables | C75: Fruits | D75: Meats | F75: Fruits | H75: Strawberry
B76: Arugula | C76: Apple | D76: Beef
B77: Asparagus | C77: Cherry | D77: Chicken
B78: Beet | C78: Lemon | D78: Lamb
B79: Broccoli | C79: Orange | D79: Pork
B80: Carrot | C80: Peach
B81: Cauliflower | C81: Pear
B82: Celery | C82: Raspberry
B83: Corn | C83: Strawberry
B84: Green Bean | C84: Kiwi
B87: Grade table data validation
B88: Name of Employee | C88: Grade | D88: Salary
B89: Ghate Akash Ramesh | C89: Lieutenant | D89: 25000 | G89: Grade | H89: Minimum | I89: Maximum
B90: Budhwani Meehir Suresh | C90: Major | D90: 39000 | G90: Lieutenant | H90: 15600 | I90: 39100
B91: Beldare Apoorva Vijay | C91: Captain | D91: 30000 | G91: Major | H91: 17000 | I91: 39100
B92: Ghoman Bhagyashri Ramesh | C92: LT Colonel | D92: 35000 | G92: Captain | H92: 20000 | I92: 45000
B93: Adhav Ajay Waman | C93: Colonel | D93: 40000 | G93: LT Colonel | H93: 25000 | I93: 67000
B94: Bharate Farhin Vasantha | C94: Brigadier | D94: 80000 | G94: Colonel | H94: 30000 | I94: 70000
B95: Godhane Debolina Ramchandra | C95: Major General | D95: 70000 | G95: Brigadier | H95: 37000 | I95: 85000
B96: Chaudhari Neha Sunil | C96: Lieutenant | D96: 35000 | G96: Major General | H96: 38500 | I96: 90000
B97: Chaudhary Nikita Sunil | C97: Major | D97: 39000
B98: Kumar Yash Adesh | C98: Captain | D98: 42000
B99: Shekhar Vaibhavi Ajay | C99: LT Colonel | D99: 60000
B100: Dhananjay Sukanya Ajay | C100: Colonel | D100: 55000
B101: Ritesh Shivani Ajit | C101: Brigadier | D101: 70000
B102: Garud RIitesh Ashish | C102: Major General | D102: 75000
B103: Deshpande Priyanka Ashok | C103: Major | D103: 35000
